wdig/__init__.py
wdig/__main__.py
wdig/cli_config.py
wdig/cli_files.py
wdig/config.py
wdig/database.py
wdig/database_v2.py
wdig/enrich/__init__.py
wdig/enrich/adjustments.py
wdig/enrich/budget_mapping.py
wdig/enrich/budget_mapping_debt.py
wdig/enrich/budget_mapping_donations.py
wdig/enrich/budget_mapping_fixed.py
wdig/enrich/budget_mapping_income.py
wdig/enrich/budget_mapping_mortgage.py
wdig/enrich/budget_mapping_savings.py
wdig/enrich/budget_mapping_transfer.py
wdig/enrich/budget_mapping_variable.py
wdig/enrich/categories.py
wdig/enrich/clean_data.py
wdig/enrich/good_budget.py
wdig/enrich/merchant_type.py
wdig/enrich/periods.py
wdig/google_sheets.py
wdig/health_checks.py
wdig/load.py
wdig/loading/__init__.py
wdig/loading/load.py
wdig/loading/load_v2.py
wdig/loading/object_storage.py
wdig/loading/parse.py
wdig/object_storage.py
wdig/outputs/monthly_statement.py
wdig/parse.py
wdig/queries.py
wdig/user_notifier.py
wdig_cli-0.1.2.dist-info/METADATA
wdig_cli-0.1.2.dist-info/WHEEL
wdig_cli-0.1.2.dist-info/entry_points.txt
wdig_cli-0.1.2.dist-info/RECORD
